CCankaoshouce20171220/README.md
CCankaoshouce20171220/__init__.py
CCankaoshouce20171220/__main__.py
CCankaoshouce20171220/file.epub
CCankaoshouce20171220/index.html
CCankaoshouce20171220/css/__init__.py
CCankaoshouce20171220/css/annotations.css
CCankaoshouce20171220/css/main.css
CCankaoshouce20171220/css/normalize.css
CCankaoshouce20171220/css/popup.css
CCankaoshouce20171220/font/__init__.py
CCankaoshouce20171220/font/fontello.eot
CCankaoshouce20171220/font/fontello.svg
CCankaoshouce20171220/font/fontello.ttf
CCankaoshouce20171220/font/fontello.woff
CCankaoshouce20171220/img/__init__.py
CCankaoshouce20171220/img/annotator-glyph-sprite.png
CCankaoshouce20171220/img/annotator-icon-sprite.png
CCankaoshouce20171220/img/apple-touch-icon.png
CCankaoshouce20171220/img/cancelfullscreen.png
CCankaoshouce20171220/img/close.png
CCankaoshouce20171220/img/fullscreen.png
CCankaoshouce20171220/img/loader.gif
CCankaoshouce20171220/img/menu-icon.png
CCankaoshouce20171220/img/save.png
CCankaoshouce20171220/img/saved.png
CCankaoshouce20171220/img/settings-s.png
CCankaoshouce20171220/img/settings.png
CCankaoshouce20171220/img/star.png
CCankaoshouce20171220/js/__init__.py
CCankaoshouce20171220/js/epub.js
CCankaoshouce20171220/js/epub.min.js
CCankaoshouce20171220/js/epub.min.map
CCankaoshouce20171220/js/hooks.min.js
CCankaoshouce20171220/js/hooks.min.map
CCankaoshouce20171220/js/reader.js
CCankaoshouce20171220/js/reader.js.map
CCankaoshouce20171220/js/reader.min.js
CCankaoshouce20171220/js/reader.min.map
CCankaoshouce20171220/js/hooks/__init__.py
CCankaoshouce20171220/js/hooks/extensions/__init__.py
CCankaoshouce20171220/js/hooks/extensions/highlight.js
CCankaoshouce20171220/js/libs/__init__.py
CCankaoshouce20171220/js/libs/jquery.min.js
CCankaoshouce20171220/js/libs/localforage.min.js
CCankaoshouce20171220/js/libs/screenfull.js
CCankaoshouce20171220/js/libs/screenfull.min.js
CCankaoshouce20171220/js/libs/zip.min.js
CCankaoshouce20171220/js/plugins/__init__.py
c_cankaoshouce_2017_12_20-2024.3.1.0.dist-info/METADATA
c_cankaoshouce_2017_12_20-2024.3.1.0.dist-info/WHEEL
c_cankaoshouce_2017_12_20-2024.3.1.0.dist-info/entry_points.txt
c_cankaoshouce_2017_12_20-2024.3.1.0.dist-info/top_level.txt
c_cankaoshouce_2017_12_20-2024.3.1.0.dist-info/RECORD
